{"matchCount":3,"bbqList":[{"address":"Todd Rd, Port Melbourne VIC","name":"WESTGATE PARK","fbUid":"603421317","longitude":144.90808010101318,"bbqId":22001,"latitude":-37.83183265528548,"type":"Unknown","distanceToBbq":"1.3","fbName":"Andrew Dyster"},{"address":"Port Melbourne VIC","name":"MURPHY RESERVE","fbUid":"100000117802502","longitude":144.929301738739,"bbqId":4673443035348992,"latitude":-37.83359857196083,"type":"Unknown","distanceToBbq":"1.1","fbName":"fb-user"},{"address":"The Boulevard, Port Melbourne VIC","name":"WESTPORT RESERVE","fbUid":"603421317","longitude":144.92224216461182,"bbqId":5074,"latitude":-37.83949256275584,"type":"Electric","distanceToBbq":"0.3","fbName":"Andrew Dyster"}]}
